eradicate.py
eradicate-3.0.0.dist-info/METADATA
eradicate-3.0.0.dist-info/WHEEL
eradicate-3.0.0.dist-info/entry_points.txt
eradicate-3.0.0.dist-info/top_level.txt
eradicate-3.0.0.dist-info/RECORD
