Metadata-Version: 2.1
Name: eradicate
Version: 3.0.0
Summary: Removes commented-out code.
Home-page: https://github.com/pycqa/eradicate
Author: Steven Myint
Maintainer: Nikita Sobolev <mail@sobolevn.me>
License: Expat License
Keywords: clean,format,commented-out code
Classifier: Environment :: Console
Classifier: Intended Audience :: Developers
Classifier: License :: OSI Approved :: MIT License
Classifier: Programming Language :: Python :: 3
Classifier: Programming Language :: Python :: 3 :: Only
Classifier: Topic :: Software Development :: Quality Assurance
